DESC.md
MANIFEST.in
README.md
setup.py
bin/bench.py
bin/dsinit.py
irbench.egg-info/PKG-INFO
irbench.egg-info/SOURCES.txt
irbench.egg-info/dependency_links.txt
irbench.egg-info/requires.txt
irbench.egg-info/top_level.txt
src/__init__.py
src/dataset.py
src/distance.py
src/evaluate.py
src/feature.py
src/index.py
src/utils.py
tools/bow2sparse.py
tools/bow2sparsedir.py