Metadata-Version: 1.0
Name: irbench
Version: 0.0.67
Summary: Image Retrieval Benchmark.
Home-page: https://github.com/wanji/irbench
Author: WAN Ji
Author-email: wanji@live.com
License: UNKNOWN
Platform: UNKNOWN
